[
 {
  "file": "library/tools/financial-crypto/nft-provenance/opensea.md",
  "id": "opensea",
  "name": "OpenSea",
  "url": "https://opensea.io/",
  "category": "financial-crypto",
  "mp": "medium"
 },
 {
  "file": "library/tools/financial-crypto/bitcoin/orbit.md",
  "id": "orbit",
  "name": "Orbit",
  "url": "https://github.com/s0md3v/Orbit",
  "category": "financial-crypto",
  "mp": "medium"
 },
 {
  "file": "library/tools/financial-crypto/osint-assassin.md",
  "id": "osint-assassin",
  "name": "OSINT-Assassin",
  "url": "https://start.me/u/l61Bqy",
  "category": "financial-crypto",
  "mp": "medium"
 },
 {
  "file": "library/tools/financial-crypto/chain-analysis-platforms/oxt-me.md",
  "id": "oxt-me",
  "name": "OXT.me",
  "url": "https://oxt.me/",
  "category": "financial-crypto",
  "mp": "medium"
 },
 {
  "file": "library/tools/financial-crypto/palatine-co-uk.md",
  "id": "palatine-co-uk",
  "name": "palatine.co.uk",
  "url": "https://www.palatine.co.uk/",
  "category": "financial-crypto",
  "mp": "medium"
 },
 {
  "file": "library/tools/financial-crypto/radixdlt-com.md",
  "id": "radixdlt-com",
  "name": "radixdlt.com",
  "url": "https://dashboard.radixdlt.com/",
  "category": "financial-crypto",
  "mp": "medium"
 },
 {
  "file": "library/tools/financial-crypto/reddit-com.md",
  "id": "reddit-com",
  "name": "reddit.com",
  "url": "https://www.reddit.com/r/OSINT/comments/1dozqu2/binance_can_be_osint_tool/",
  "category": "financial-crypto",
  "mp": "medium"
 },
 {
  "file": "library/tools/financial-crypto/researchgate-net.md",
  "id": "researchgate-net",
  "name": "researchgate.net",
  "url": "https://www.researchgate.net/publication/319944399_An_Analysis_of_Bitcoin_Laundry_Services",
  "category": "financial-crypto",
  "mp": "medium"
 },
 {
  "file": "library/tools/financial-crypto/robert-devere-bunn.md",
  "id": "robert-devere-bunn",
  "name": "Robert Devere Bunn",
  "url": "https://www.linkedin.com/in/robertdeverebunn/",
  "category": "financial-crypto",
  "mp": "medium"
 },
 {
  "file": "library/tools/financial-crypto/secjuice-com.md",
  "id": "secjuice-com",
  "name": "secjuice.com",
  "url": "https://www.secjuice.com/crypto-osint/",
  "category": "financial-crypto",
  "mp": "medium"
 },
 {
  "file": "library/tools/financial-crypto/secjuice-com-2.md",
  "id": "secjuice-com-2",
  "name": "secjuice.com",
  "url": "https://www.secjuice.com/crypto-osint-wallet-research/",
  "category": "financial-crypto",
  "mp": "medium"
 },
 {
  "file": "library/tools/financial-crypto/sortcodes-co-uk.md",
  "id": "sortcodes-co-uk",
  "name": "sortcodes.co.uk",
  "url": "https://www.sortcodes.co.uk/sort-code-checker",
  "category": "financial-crypto",
  "mp": "medium"
 },
 {
  "file": "library/tools/financial-crypto/sortcodes-co-uk-2.md",
  "id": "sortcodes-co-uk-2",
  "name": "sortcodes.co.uk",
  "url": "https://www.sortcodes.co.uk/",
  "category": "financial-crypto",
  "mp": "medium"
 },
 {
  "file": "library/tools/financial-crypto/start-me.md",
  "id": "start-me",
  "name": "start.me",
  "url": "https://start.me/p/Bnmdyv/crypto-resources",
  "category": "financial-crypto",
  "mp": "medium"
 },
 {
  "file": "library/tools/financial-crypto/start-me-2.md",
  "id": "start-me-2",
  "name": "start.me",
  "url": "https://start.me/p/eppylY/finint-cryptocurrency",
  "category": "financial-crypto",
  "mp": "medium"
 },
 {
  "file": "library/tools/financial-crypto/thenextweb-com.md",
  "id": "thenextweb-com",
  "name": "thenextweb.com",
  "url": "https://thenextweb.com/news/bitcoin-money-laundering-2",
  "category": "financial-crypto",
  "mp": "medium"
 }
]