[
 {
  "file": "library/tools/messaging/passwordsearch.md",
  "id": "passwordsearch",
  "name": "PasswordSearch",
  "url": "https://telegram.me/PasswordSearchBot",
  "category": "messaging",
  "mp": "high"
 },
 {
  "file": "library/tools/messaging/pimeyes.md",
  "id": "pimeyes",
  "name": "PimEyes",
  "url": "https://telegram.me/pimeyesbot",
  "category": "messaging",
  "mp": "high"
 },
 {
  "file": "library/tools/messaging/pixelatomy-com.md",
  "id": "pixelatomy-com",
  "name": "pixelatomy.com",
  "url": "https://pixelatomy.com/snow-stamp/",
  "category": "messaging",
  "mp": "high"
 },
 {
  "file": "library/tools/messaging/prankshit-com-2.md",
  "id": "prankshit-com-2",
  "name": "prankshit.com",
  "url": "https://prankshit.com/fake-whatsapp-chat-generator.php",
  "category": "messaging",
  "mp": "high"
 },
 {
  "file": "library/tools/messaging/prime-os-emuapps-com.md",
  "id": "prime-os-emuapps-com",
  "name": "prime-os.emuapps.com",
  "url": "https://prime-os.emuapps.com/",
  "category": "messaging",
  "mp": "high"
 },
 {
  "file": "library/tools/messaging/pts-project-org.md",
  "id": "pts-project-org",
  "name": "pts-project.org",
  "url": "https://pts-project.org/blog/analysis-of-botim-v3.38.1/",
  "category": "messaging",
  "mp": "high"
 },
 {
  "file": "library/tools/messaging/rapidapi-com.md",
  "id": "rapidapi-com",
  "name": "rapidapi.com",
  "url": "https://rapidapi.com/inutil-inutil-default/api/whatsapp-osint",
  "category": "messaging",
  "mp": "high"
 },
 {
  "file": "library/tools/messaging/reddit-com-2.md",
  "id": "reddit-com-2",
  "name": "reddit.com",
  "url": "https://www.reddit.com/r/Telegram/comments/1f2p61w/how_to_find_another_users_id/",
  "category": "messaging",
  "mp": "high"
 },
 {
  "file": "library/tools/messaging/reddit-com-3.md",
  "id": "reddit-com-3",
  "name": "reddit.com",
  "url": "https://www.reddit.com/r/Telegram/comments/7znf6s/how_do_i_find_my_telegram_id/",
  "category": "messaging",
  "mp": "high"
 },
 {
  "file": "library/tools/messaging/regdatebot.md",
  "id": "regdatebot",
  "name": "RegDateBot",
  "url": "https://t.me/regdate_clone_bot",
  "category": "messaging",
  "mp": "high"
 },
 {
  "file": "library/tools/messaging/sangmata-beta.md",
  "id": "sangmata-beta",
  "name": "SangMata (beta)",
  "url": "https://t.me/SangMata_beta_bot",
  "category": "messaging",
  "mp": "high"
 },
 {
  "file": "library/tools/messaging/sangmatainfo-bot.md",
  "id": "sangmatainfo-bot",
  "name": "SangMataInfo_bot",
  "url": "https://t.me/SangMataInfo_bot",
  "category": "messaging",
  "mp": "high"
 },
 {
  "file": "library/tools/messaging/saveyoutubebot.md",
  "id": "saveyoutubebot",
  "name": "SaveYoutubeBot",
  "url": "https://t.me/SaveYoutubeBot",
  "category": "messaging",
  "mp": "high"
 },
 {
  "file": "library/tools/messaging/search-firm-bot.md",
  "id": "search-firm-bot",
  "name": "Search_firm_bot",
  "url": "https://t.me/Search_firm_bot",
  "category": "messaging",
  "mp": "high"
 },
 {
  "file": "library/tools/messaging/searchforchats.md",
  "id": "searchforchats",
  "name": "Searchforchats",
  "url": "https://telegram.me/searchforchatsbot",
  "category": "messaging",
  "mp": "high"
 },
 {
  "file": "library/tools/messaging/sherlock-3.md",
  "id": "sherlock-3",
  "name": "Sherlock",
  "url": "https://t.me/Getcontact123qwerty_bot?start=_ref_jGW8Sa_iEmG9V",
  "category": "messaging",
  "mp": "high"
 }
]