[
 {
  "file": "library/tools/username/specific-sites/keybase.md",
  "id": "keybase",
  "name": "Keybase",
  "url": "https://keybase.io/",
  "category": "username",
  "mp": "high"
 },
 {
  "file": "library/tools/username/username-search-engines/lullar.md",
  "id": "lullar",
  "name": "Lullar",
  "url": "https://com.lullar.com",
  "category": "username",
  "mp": "high"
 },
 {
  "file": "library/tools/username/maigret.md",
  "id": "maigret",
  "name": "Maigret",
  "url": "https://github.com/soxoj/maigret",
  "category": "username",
  "mp": "high"
 },
 {
  "file": "library/tools/username/specific-sites/mit-pgp-key-server.md",
  "id": "mit-pgp-key-server",
  "name": "MIT PGP Key Server",
  "url": "https://pgp.mit.edu/",
  "category": "username",
  "mp": "high"
 },
 {
  "file": "library/tools/username/name-checkr.md",
  "id": "name-checkr",
  "name": "Name Checkr",
  "url": "http://www.namecheckr.com",
  "category": "username",
  "mp": "high"
 },
 {
  "file": "library/tools/username/name-chk.md",
  "id": "name-chk",
  "name": "Name Chk",
  "url": "http://www.namechk.com",
  "category": "username",
  "mp": "high"
 },
 {
  "file": "library/tools/username/namecheck.md",
  "id": "namecheck",
  "name": "Namecheck",
  "url": "https://namecheck.bloggingehow.com",
  "category": "username",
  "mp": "high"
 },
 {
  "file": "library/tools/username/username-search-engines/namecheckup.md",
  "id": "namecheckup",
  "name": "NameCheckup",
  "url": "https://namecheckup.com/",
  "category": "username",
  "mp": "high"
 },
 {
  "file": "library/tools/username/username-search-engines/namechk.md",
  "id": "namechk",
  "name": "Namechk",
  "url": "https://namechk.com/",
  "category": "username",
  "mp": "high"
 },
 {
  "file": "library/tools/username/namechk-2.md",
  "id": "namechk-2",
  "name": "Namechk",
  "url": "https://github.com/ha71/namechk",
  "category": "username",
  "mp": "high"
 },
 {
  "file": "library/tools/username/nameketchup.md",
  "id": "nameketchup",
  "name": "NameKetchup",
  "url": "https://nameketchup.com",
  "category": "username",
  "mp": "high"
 },
 {
  "file": "library/tools/username/username-search-engines/names-directory.md",
  "id": "names-directory",
  "name": "Names Directory",
  "url": "https://namesdir.com/",
  "category": "username",
  "mp": "high"
 },
 {
  "file": "library/tools/username/namevine-user-name-search.md",
  "id": "namevine-user-name-search",
  "name": "NameVine (User Name Search)",
  "url": "https://namevine.com",
  "category": "username",
  "mp": "high"
 },
 {
  "file": "library/tools/username/nexfil.md",
  "id": "nexfil",
  "name": "NexFil",
  "url": "https://github.com/thewhiteh4t/nexfil",
  "category": "username",
  "mp": "high"
 },
 {
  "file": "library/tools/username/ok-ru.md",
  "id": "ok-ru",
  "name": "ok.ru",
  "url": "https://ok.ru/dk?st.cmd=anonymRecoveryStart",
  "category": "username",
  "mp": "high"
 },
 {
  "file": "library/tools/username/osint-toolkit.md",
  "id": "osint-toolkit",
  "name": "OSINT Toolkit",
  "url": "https://one-plus.github.io/EmailUsername",
  "category": "username",
  "mp": "high"
 }
]